{
  "AssemblySemFileVer": "0.3.5.0",
  "AssemblySemVer": "0.3.5.0",
  "BranchName": "master",
  "BuildMetaData": null,
  "CommitDate": "2025-07-14",
  "CommitsSinceVersionSource": 2,
  "EscapedBranchName": "master",
  "FullBuildMetaData": "Branch.master.Sha.3bc91ad0ac7361bddd91e5b1340517c33044f860",
  "FullSemVer": "0.3.5-2",
  "InformationalVersion": "0.3.5-2+Branch.master.Sha.3bc91ad0ac7361bddd91e5b1340517c33044f860",
  "Major": 0,
  "MajorMinorPatch": "0.3.5",
  "Minor": 3,
  "Patch": 5,
  "PreReleaseLabel": "",
  "PreReleaseLabelWithDash": "",
  "PreReleaseNumber": 2,
  "PreReleaseTag": "2",
  "PreReleaseTagWithDash": "-2",
  "SemVer": "0.3.5-2",
  "Sha": "3bc91ad0ac7361bddd91e5b1340517c33044f860",
  "ShortSha": "3bc91ad",
  "UncommittedChanges": 0,
  "VersionSourceSha": "e2dc6839870b621a3b6acdfea3643b6b94923c02",
  "WeightedPreReleaseNumber": 55002
}