{
  "AssemblySemFileVer": "0.3.4.0",
  "AssemblySemVer": "0.3.4.0",
  "BranchName": "master",
  "BuildMetaData": null,
  "CommitDate": "2025-07-11",
  "CommitsSinceVersionSource": 1,
  "EscapedBranchName": "master",
  "FullBuildMetaData": "Branch.master.Sha.24cc75548c37365e9e2197d10fd3227a4f4d6b3b",
  "FullSemVer": "0.3.4-1",
  "InformationalVersion": "0.3.4-1+Branch.master.Sha.24cc75548c37365e9e2197d10fd3227a4f4d6b3b",
  "Major": 0,
  "MajorMinorPatch": "0.3.4",
  "Minor": 3,
  "Patch": 4,
  "PreReleaseLabel": "",
  "PreReleaseLabelWithDash": "",
  "PreReleaseNumber": 1,
  "PreReleaseTag": "1",
  "PreReleaseTagWithDash": "-1",
  "SemVer": "0.3.4-1",
  "Sha": "24cc75548c37365e9e2197d10fd3227a4f4d6b3b",
  "ShortSha": "24cc755",
  "UncommittedChanges": 0,
  "VersionSourceSha": "4241febaa887504368060f98ef92c51505d581c8",
  "WeightedPreReleaseNumber": 55001
}